colombiaHolidays/__init__.py
colombiaHolidays/holidays.py
colombiaHolidays-0.0.2.dist-info/LICENSE
colombiaHolidays-0.0.2.dist-info/METADATA
colombiaHolidays-0.0.2.dist-info/WHEEL
colombiaHolidays-0.0.2.dist-info/top_level.txt
colombiaHolidays-0.0.2.dist-info/RECORD
